pokecov/__init__.py
pokecov/check.py
pokecov/coverage.py
pokecov/gen1.csv
pokecov/gen2.csv
pokecov/gen6.csv
pokecov/logger.py
pokecov/py.typed
pokecov/search.py
pokecov-1.0.1.dist-info/LICENSE
pokecov-1.0.1.dist-info/METADATA
pokecov-1.0.1.dist-info/WHEEL
pokecov-1.0.1.dist-info/entry_points.txt
pokecov-1.0.1.dist-info/top_level.txt
pokecov-1.0.1.dist-info/RECORD
