Metadata-Version: 2.1
Name: pokecov
Version: 1.0.1
Summary: Tool to check the effectiveness and coverage of your pokemon attacks
Author-email: Pradish Bijukchhe <pradishbijukchhe@gmail.com>
License: Copyright (c) 2018 The Python Packaging Authority
Project-URL: Homepage, https://github.com/pradishb/pokecov
Project-URL: Issues, https://github.com/pradishb/pokecov/issues
Classifier: Programming Language :: Python :: 3
Requires-Python: >=3
License-File: LICENSE
